uaal_verify/__init__.py
uaal_verify/cli.py
uaal_verify/day.py
uaal_verify/hashing.py
uaal_verify/range.py
uaal_verify/record.py
uaal_verify-0.1.2.dist-info/METADATA
uaal_verify-0.1.2.dist-info/WHEEL
uaal_verify-0.1.2.dist-info/entry_points.txt
uaal_verify-0.1.2.dist-info/top_level.txt
uaal_verify-0.1.2.dist-info/RECORD
