Metadata-Version: 2.4
Name: uaal-verify
Version: 0.1.2
Summary: Independent verification toolkit for UAAL decision evidence
Author-email: UAAL <info@lolasolution.com>
License: Apache-2.0
Classifier: Programming Language :: Python :: 3
Classifier: License :: OSI Approved :: Apache Software License
Classifier: Intended Audience :: Developers
Classifier: Intended Audience :: Financial and Insurance Industry
Classifier: Topic :: Security :: Cryptography
Classifier: Topic :: Software Development :: Testing
Requires-Python: >=3.9
